tipsql/snowflake/__init__.py
tipsql/snowflake/connection.py
tipsql/snowflake/cursor.py
tipsql/snowflake/data/.gitignore
tipsql/snowflake/datatype/__init__.py
tipsql/snowflake/datatype/binary.py
tipsql/snowflake/datatype/boolean.py
tipsql/snowflake/datatype/datetime.py
tipsql/snowflake/datatype/float.py
tipsql/snowflake/datatype/number.py
tipsql/snowflake/datatype/string.py
tipsql/snowflake/datatype/variant.py
tipsql/snowflake/plugin.py
tipsql/snowflake/query/__init__.py
tipsql/snowflake/query/builder.py
tipsql/snowflake/relation.py
tipsql/snowflake/templates/__init__.py
tipsql/snowflake/templates/relation.py.jinja
tipsql_snowflake-0.0.5.dist-info/METADATA
tipsql_snowflake-0.0.5.dist-info/WHEEL
tipsql_snowflake-0.0.5.dist-info/entry_points.txt
tipsql_snowflake-0.0.5.dist-info/RECORD
