Metadata-Version: 2.1
Name: tipsql-snowflake
Version: 0.0.5
Summary: tipsql adapter for Snowflake
Author: yassun7010
Author-email: yassun7010@outlook.com
Requires-Python: >=3.12,<4.0
Classifier: Programming Language :: Python :: 3
Classifier: Programming Language :: Python :: 3.12
Requires-Dist: snowflake-connector-python (>=3.3.1,<4.0.0)
Requires-Dist: tipsql-core (==0.0.5)
